pretty_assert/__init__.py
pretty_assert-0.1.1.dist-info/LICENSE
pretty_assert-0.1.1.dist-info/METADATA
pretty_assert-0.1.1.dist-info/WHEEL
pretty_assert-0.1.1.dist-info/RECORD
