Metadata-Version: 2.1
Name: pretty-assert
Version: 0.1.1
Summary: A python package to print pretty, user-friendly assertions.
License: MIT
Keywords: assertion,pretty,user
Author: lxl66566
Author-email: lxl66566@gmail.com
Requires-Python: >=3.8,<4.0
Classifier: License :: OSI Approved :: MIT License
Classifier: Operating System :: OS Independent
Classifier: Programming Language :: Python :: 3
Classifier: Programming Language :: Python :: 3.8
Classifier: Programming Language :: Python :: 3.9
Classifier: Programming Language :: Python :: 3.10
Classifier: Programming Language :: Python :: 3.11
Classifier: Programming Language :: Python :: 3.12
Classifier: Topic :: Printing
Classifier: Topic :: Utilities
Requires-Dist: icdiff (>=2.0.7,<3.0.0)
Requires-Dist: pprintpp (>=0.4.0,<0.5.0)
Requires-Dist: termcolor (>=2.4.0,<3.0.0)
